<keymap version="1" name="Default copy" parent="Mac OS X 10.5+">
  <action id="ActivateDatabaseToolWindow">
    <keyboard-shortcut first-keystroke="meta 0" />
  </action>
  <action id="ActivateMessagesToolWindow" />
  <action id="EditorCloneCaretBelow">
    <keyboard-shortcut first-keystroke="ctrl alt down" />
  </action>
  <action id="PhpListenDebugAction">
    <keyboard-shortcut first-keystroke="shift meta l" />
  </action>
  <action id="SearchEverywhere">
    <keyboard-shortcut first-keystroke="shift meta p" />
  </action>
</keymap>